<?xml version="1.0" encoding="utf-8"?>
<LanguageData>
  <Interaction_KiiroCuddle.label>키이로 쓰다듬기</Interaction_KiiroCuddle.label>
  <Interaction_KiiroCuddle_Ratkin.label>키이로 쓰다듬기</Interaction_KiiroCuddle_Ratkin.label>
  <Interaction_KiiroCuddle_MoeLotl.label>키이로 쓰다듬기</Interaction_KiiroCuddle_MoeLotl.label>
  <Interaction_KiiroCuddle_Kiiro.label>키이로 쓰다듬기</Interaction_KiiroCuddle_Kiiro.label>
  <Interaction_KiiroCuddle_Cinder.label>키이로 쓰다듬기</Interaction_KiiroCuddle_Cinder.label>
  <Interaction_KiiroCuddle_Bunny.label>키이로 쓰다듬기</Interaction_KiiroCuddle_Bunny.label>
  <Interaction_KiiroCuddle_Common.label>키이로 쓰다듬기</Interaction_KiiroCuddle_Common.label>
</LanguageData>