<?xml version="1.0" encoding="utf-8"?>
<LanguageData>
  <Apparel_KidTribalCape.description>바깥의 모래와 햇빛을 피하는 용도의 단순하고 기다란 털가죽 망토입니다.</Apparel_KidTribalCape.description>
  <Apparel_KidTribalCape.label>아동용 부족 망토</Apparel_KidTribalCape.label>
  <Apparel_KidTribalCloak.description>생채기와 멍, 쌀쌀한 날씨로부터 따듯하게 지켜 주는 가죽을 덧대어 만든 단순한 덧옷입니다. </Apparel_KidTribalCloak.description>
  <Apparel_KidTribalCloak.label>아동용 부족 덧옷</Apparel_KidTribalCloak.label>
  <Apparel_KidTribalFurCloak.label>아동용 부족 털가죽 덧옷</Apparel_KidTribalFurCloak.label>
  <Apparel_KidTribalFurCloak.description>여러 겹의 모피와 가죽을 덧대어 만든 두꺼운 옷으로서, 혹한의 날씨를 제외하고는 따듯하게 날 수 있습니다.</Apparel_KidTribalFurCloak.description>
  <Apparel_TribalCape.description>바깥의 모래와 햇빛을 피하는 용도의 단순하고 기다란 털가죽 망토입니다.</Apparel_TribalCape.description>
  <Apparel_TribalCape.label>부족 망토</Apparel_TribalCape.label>
  <Apparel_TribalCloak.label>부족 덧옷</Apparel_TribalCloak.label>
  <Apparel_TribalCloak.description>생채기와 멍, 쌀쌀한 날씨로부터 따듯하게 지켜 주는 가죽을 덧대어 만든 단순한 덧옷입니다. </Apparel_TribalCloak.description>
  <Apparel_TribalFurCloak.label>부족 털가죽 덧옷</Apparel_TribalFurCloak.label>
  <Apparel_TribalFurCloak.description>여러 겹의 모피와 가죽을 덧대어 만든 두꺼운 옷으로서, 혹한의 날씨를 제외하고는 따듯하게 날 수 있습니다.</Apparel_TribalFurCloak.description>
</LanguageData>